pyGeoPressure-0.1.10.dist-info/METADATA
pyGeoPressure-0.1.10.dist-info/RECORD
pyGeoPressure-0.1.10.dist-info/WHEEL
pyGeoPressure-0.1.10.dist-info/top_level.txt
pygeopressure/__init__.py
pygeopressure/_version.py
pygeopressure/basic/__init__.py
pygeopressure/basic/horizon.py
pygeopressure/basic/indexes.py
pygeopressure/basic/las.py
pygeopressure/basic/las_reader.py
pygeopressure/basic/log_tools.py
pygeopressure/basic/optimizer.py
pygeopressure/basic/plots.py
pygeopressure/basic/seisegy.py
pygeopressure/basic/survey.py
pygeopressure/basic/survey_setting.py
pygeopressure/basic/threepoints.py
pygeopressure/basic/utils.py
pygeopressure/basic/vawt.py
pygeopressure/basic/well.py
pygeopressure/basic/well_log.py
pygeopressure/basic/well_storage.py
pygeopressure/pressure/__init__.py
pygeopressure/pressure/bowers.py
pygeopressure/pressure/bowers_seis.py
pygeopressure/pressure/eaton.py
pygeopressure/pressure/eaton_seis.py
pygeopressure/pressure/hydrostatic.py
pygeopressure/pressure/multivariate.py
pygeopressure/pressure/obp.py
pygeopressure/pressure/utils.py
pygeopressure/velocity/__init__.py
pygeopressure/velocity/conversion.py
pygeopressure/velocity/extrapolate.py
pygeopressure/velocity/interpolation.py
pygeopressure/velocity/smoothing.py
