Metadata-Version: 2.1
Name: pyGeoPressure
Version: 0.1.10
Summary: pyGeoPressure: Tools for geopressure prediction
Home-page: https://github.com/whimian/pyGeoPressure
Author: Yu Hao
Author-email: yuhao@live.cn
License: MIT
Download-URL: https://github.com/whimian/pyGeoPressure
Keywords: pore pressure prediction
Platform: Windows
Platform: Linux
Platform: Solaris
Platform: Mac OS-X
Platform: Unix
Classifier: Development Status :: 4 - Beta
Classifier: Intended Audience :: Developers
Classifier: Intended Audience :: Science/Research
Classifier: License :: OSI Approved :: MIT License
Classifier: Programming Language :: Python
Classifier: Topic :: Scientific/Engineering
Classifier: Topic :: Scientific/Engineering :: Mathematics
Classifier: Topic :: Scientific/Engineering :: Physics
Classifier: Operating System :: Microsoft :: Windows
Classifier: Operating System :: POSIX
Classifier: Operating System :: Unix
Classifier: Operating System :: MacOS
Classifier: Natural Language :: English
Requires-Python: >=2.7, <3.7
Requires-Dist: future
Requires-Dist: scipy
Requires-Dist: scikit-learn
Requires-Dist: pandas
Requires-Dist: tables
Requires-Dist: segyio
Requires-Dist: pathlib2; python_version == "2.7"
Requires-Dist: singledispatch; python_version == "2.7"
Requires-Dist: matplotlib (<3.0); python_version == "2.7"
Requires-Dist: matplotlib; python_version > "2.7"
